plugin_mongo/__init__.py
plugin_mongo/plugin.py
pyproject.toml
tests/__init__.py
tests/test_dep_plugin_mongo.py
dep_plugin_mongo-0.1.4.dist-info/WHEEL
dep_plugin_mongo-0.1.4.dist-info/METADATA
dep_plugin_mongo-0.1.4.dist-info/RECORD
