Metadata-Version: 2.1
Name: dep-plugin-mongo
Version: 0.1.4
Summary: 
Author: everhide
Author-email: i.tolkachnikov@gmail.com
Requires-Python: >=3.9,<4.0
Classifier: Programming Language :: Python :: 3
Classifier: Programming Language :: Python :: 3.10
Classifier: Programming Language :: Python :: 3.9
Requires-Dist: dep-spec (==0.4.0)
Requires-Dist: motor (>=3.0.0,<4.0.0)
